ising/__init__.py
ising/client.py
ising/request/GeneralTaskCreateRequest.py
ising/request/TemplateTaskCreateRequest.py
ising/request/__init__.py
ising_sdk-1.0.9.dist-info/METADATA
ising_sdk-1.0.9.dist-info/WHEEL
ising_sdk-1.0.9.dist-info/top_level.txt
ising_sdk-1.0.9.dist-info/RECORD
