Metadata-Version: 2.1
Name: ising-sdk
Version: 1.0.9
Summary: Python SDK for Ising Cloud Service
Home-page: UNKNOWN
Author: ising
Author-email: haojunjie@isingtech.com
License: UNKNOWN
Platform: UNKNOWN
Classifier: Programming Language :: Python :: 3
Classifier: License :: OSI Approved :: MIT License
Classifier: Operating System :: OS Independent
Requires-Python: >=3.6
Requires-Dist: requests>=2.22.0
